LSC_Client/LSC_Client.py
LSC_Client/__init__.py
ddm_robot/LSC_Client.py
ddm_robot/__init__.py
ddm_robot/ddm_robot.py
ddm_robot/robot.py
ddm_robot/showlib.py
ddm_robot/voice.py
example/__init__.py
example/f1.py
example/f2.py
robot/LSC_Client.py
robot/__init__.py
robot/get_ip.py
robot/lsc.py
robot/makeros.py
robot/robot.py
robot/shortshow.py
robot/showlib.py
robot/voice.py
ddm_robot-0.0.1.dist-info/METADATA
ddm_robot-0.0.1.dist-info/WHEEL
ddm_robot-0.0.1.dist-info/top_level.txt
ddm_robot-0.0.1.dist-info/RECORD
