Metadata-Version: 2.1
Name: ddm-robot
Version: 0.0.1
Summary: This is a packege for ddm_robot
Home-page: https://github.com/NocoldBob/robot
Author: Bob He
Author-email: fastbiubiu@163.com
License: UNKNOWN
Platform: UNKNOWN
Classifier: Programming Language :: Python :: 3
Classifier: License :: OSI Approved :: MIT License
Classifier: Operating System :: OS Independent
